peblar/__init__.py
peblar/const.py
peblar/exceptions.py
peblar/models.py
peblar/peblar.py
peblar/py.typed
peblar/utils.py
peblar/cli/__init__.py
peblar/cli/async_typer.py
peblar/cli/ruff.toml
peblar-0.4.0.dist-info/METADATA
peblar-0.4.0.dist-info/WHEEL
peblar-0.4.0.dist-info/entry_points.txt
peblar-0.4.0.dist-info/licenses/LICENSE.md
peblar-0.4.0.dist-info/RECORD
