Metadata-Version: 2.4
Name: peblar
Version: 0.4.0
Summary: Asynchronous Python client for Peblar EV chargers.
Project-URL: Changelog, https://github.com/frenck/python-peblar/releases
Project-URL: Issues, https://github.com/frenck/python-peblar/issues
Project-URL: Repository, https://github.com/frenck/python-peblar
Author-email: Franck Nijhof <opensource@frenck.dev>
Maintainer-email: Franck Nijhof <opensource@frenck.dev>
License: MIT License
License-File: LICENSE.md
Keywords: bluebuilt,charger,chargers,ev,hybrid,ocpp,peblar
Classifier: Development Status :: 3 - Alpha
Classifier: Framework :: AsyncIO
Classifier: Intended Audience :: Developers
Classifier: Natural Language :: English
Classifier: Programming Language :: Python :: 3
Classifier: Programming Language :: Python :: 3.11
Classifier: Programming Language :: Python :: 3.12
Classifier: Programming Language :: Python :: 3.13
Classifier: Topic :: Software Development :: Libraries :: Python Modules
Requires-Python: >=3.11
Requires-Dist: aiohttp>=3.0.0
Requires-Dist: awesomeversion>=22.8.0
Requires-Dist: backoff>=2.2.1
Requires-Dist: mashumaro>=3.10
Requires-Dist: orjson>=3.9.8
Requires-Dist: yarl>=1.6.0
Provides-Extra: cli
Requires-Dist: typer>=0.15.1; extra == 'cli'
Requires-Dist: zeroconf>=0.126.0; extra == 'cli'
